{
 "results": [ 
   {
      "sectionHeader": "Personal Records",
     "type": "Records",
     "cardsInfo": [{
       "type": "record",
       "metaData": {
         "imageUrl":"https://raw.githubusercontent.com/ravishankar03/FetchInfo/main/medal_case_assets%20(1)/personal_records_assets%20(1)/longest_run.png",
         "text":"Longent Run",
         "subText":"00:00",
         "enabled": true
       }
       
     },
     {
       "type": "record",
       "metaData": {
         "imageUrl":"https://raw.githubusercontent.com/ravishankar03/FetchInfo/main/medal_case_assets%20(1)/personal_records_assets%20(1)/highest_elevation.png",
         "text":"Highest Elevation",
         "subText":"2096 ft",
         "enabled": true
       }
     },
     {
       "type": "record",
       "metaData": {
         "imageUrl":"https://raw.githubusercontent.com/ravishankar03/FetchInfo/main/medal_case_assets%20(1)/personal_records_assets%20(1)/fastest_5k.png",
         "text":"Fastest 5k",
         "subText":"00:00",
         "enabled": true
       }
       
     },
     {
       "type": "record",
       "metaData": {
         "imageUrl":"https://raw.githubusercontent.com/ravishankar03/FetchInfo/main/medal_case_assets%20(1)/personal_records_assets%20(1)/fastest_10k.png",
         "text":"10k",
         "subText":"00:00:00",
         "enabled": true
       }
       
     },
     {
       "type": "record",
       "metaData": {
         "imageUrl":"https://raw.githubusercontent.com/ravishankar03/FetchInfo/main/medal_case_assets%20(1)/personal_records_assets%20(1)/fastest_half_marathon.png",
         "text":"Half Marathon",
         "subText":"00:00",
         "enabled": true
       }
       
     },
     {
       "type": "record",
       "metaData": {
         "imageUrl":"https://raw.githubusercontent.com/ravishankar03/FetchInfo/main/medal_case_assets%20(1)/personal_records_assets%20(1)/fastest_marathon.png",
         "text":"Marathon",
         "subText":"Not Yet",
         "enabled": false
         
       }
       
     }]
 },
   {
      "sectionHeader": "Virtual Races",
     "type": "Races",
     "cardsInfo": [{
       "type": "race",
       "metaData": {
         "imageUrl":"https://raw.githubusercontent.com/ravishankar03/FetchInfo/main/medal_case_assets%20(1)/virtual_races_assets/virtual_half_marathon_race.png",
         "text":"Virtual Half Marathon",
         "subText":"00:00",
         "enabled": true
       }
     },
     {
       "type": "race",
       "metaData": {
         "imageUrl":"https://raw.githubusercontent.com/ravishankar03/FetchInfo/main/medal_case_assets%20(1)/virtual_races_assets/tokyo_kakone_ekiden.png",
         "text":"Tokyo-Hakone Ekiden",
         "subText":"00:00:00",
         "enabled": true
       }
       
     },
     {
       "type": "race",
       "metaData": {
         "imageUrl":"https://raw.githubusercontent.com/ravishankar03/FetchInfo/main/medal_case_assets%20(1)/virtual_races_assets/virtual_10k_race.png",
         "text":"Virtual 10k Race",
         "subText":"00:00:00",
         "enabled": true
       }
       
     },
     {
       "type": "race",
       "metaData": {
         "imageUrl":"https://raw.githubusercontent.com/ravishankar03/FetchInfo/main/medal_case_assets%20(1)/virtual_races_assets/hakone_ekiden.png",
         "text":"Hakone Ekiden",
         "subText":"00:00:00",
         "enabled": true
       }
       
     },
     {
       "type": "race",
       "metaData": {
         "imageUrl":"https://raw.githubusercontent.com/ravishankar03/FetchInfo/main/medal_case_assets%20(1)/virtual_races_assets/mizuno_singapore_ekiden.png",
         "text":"Mizuno Singapore Ekiden 2015",
         "subText":"00:00:00",
         "enabled": true
       }
       
     },
     {
       "type": "race",
       "metaData": {
         "imageUrl":"https://raw.githubusercontent.com/ravishankar03/FetchInfo/main/medal_case_assets%20(1)/virtual_races_assets/virtual_5k_race.png",
         "text":"Virtual 5K Race",
         "subText":"",
         "enabled": true
       }
       
     },
     {
       "type": "race",
       "metaData": {
         "imageUrl":"https://raw.githubusercontent.com/ravishankar03/FetchInfo/main/medal_case_assets%20(1)/virtual_races_assets/virtual_marathon_race.png",
         "text":"Virtual Marathon",
         "subText":"00:00:00",
         "enabled": true
       }
       
     }]
 }
 ]
}
